crispywinner/__init__.py
crispywinner/webhooks.py
crispy_winner-1.0.2.dist-info/LICENSE
crispy_winner-1.0.2.dist-info/METADATA
crispy_winner-1.0.2.dist-info/WHEEL
crispy_winner-1.0.2.dist-info/entry_points.txt
crispy_winner-1.0.2.dist-info/top_level.txt
crispy_winner-1.0.2.dist-info/RECORD
