Metadata-Version: 2.1
Name: crispy-winner
Version: 1.0.2
Summary: Mitigate discord phishing scams by spamming their webhooks
Home-page: UNKNOWN
License: UNKNOWN
Platform: UNKNOWN
License-File: LICENSE
Requires-Dist: requests
